kfre/__init__.py
kfre/logo.py
kfre/main.py
kfre/perform_eval.py
kfre-0.1.16.dist-info/licenses/LICENSE
kfre-0.1.16.dist-info/METADATA
kfre-0.1.16.dist-info/WHEEL
kfre-0.1.16.dist-info/top_level.txt
kfre-0.1.16.dist-info/RECORD
