Metadata-Version: 2.4
Name: kfre
Version: 0.1.16
Summary: A Python library for estimating kidney failure risk using the KFRE model developed by Tangri et al.
Author: Leonid Shpaner
Author-email: Leonid Shpaner <lshpaner@ucla.edu>
License: MIT
Project-URL: Author Website, https://www.leonshpaner.com
Project-URL: Documentation, https://lshpaner.github.io/kfre/
Project-URL: Zenodo Archive, https://zenodo.org/records/11100222
Project-URL: Source Code, https://github.com/lshpaner/kfre
Classifier: Programming Language :: Python :: 3
Classifier: License :: OSI Approved :: MIT License
Classifier: Operating System :: OS Independent
Requires-Python: >=3.7.4
License-File: LICENSE
Requires-Dist: numpy>=1.18.5
Requires-Dist: pandas>=1.0.5
Requires-Dist: matplotlib>=3.2.2
Requires-Dist: seaborn>=0.10.1
Requires-Dist: scikit-learn>=0.23.1
Dynamic: author
Dynamic: license-file
Dynamic: requires-python
